{
  "chartType": "line",
  "meta": {
    "title": "Opal dragon bolts (e)",
    "description": "Daily profit trend"
  },
  "xKey": "time",
  "series": [
    {
      "dataKey": "profit",
      "label": "Profit",
      "valueFormat": "integer"
    }
  ],
  "data": [
    {
      "time": 1778918503,
      "profit": null
    },
    {
      "time": 1778922688,
      "profit": null
    },
    {
      "time": 1778943295,
      "profit": null
    },
    {
      "time": 1778947020,
      "profit": null
    },
    {
      "time": 1778958124,
      "profit": null
    },
    {
      "time": 1778964190,
      "profit": null
    },
    {
      "time": 1778998915,
      "profit": null
    },
    {
      "time": 1779008610,
      "profit": null
    },
    {
      "time": 1779023801,
      "profit": null
    },
    {
      "time": 1779029689,
      "profit": null
    },
    {
      "time": 1779044759,
      "profit": null
    },
    {
      "time": 1779050935,
      "profit": null
    },
    {
      "time": 1779075659,
      "profit": null
    },
    {
      "time": 1779107293,
      "profit": null
    },
    {
      "time": 1779253386,
      "profit": null
    },
    {
      "time": 1779542464,
      "profit": null
    },
    {
      "time": 1779634933,
      "profit": null
    },
    {
      "time": 1779641920,
      "profit": null
    },
    {
      "time": 1779918734,
      "profit": null
    },
    {
      "time": 1779923745,
      "profit": null
    },
    {
      "time": 1780544968,
      "profit": null
    },
    {
      "time": 1780595139,
      "profit": null
    },
    {
      "time": 1780617920,
      "profit": null
    },
    {
      "time": 1780700788,
      "profit": null
    },
    {
      "time": 1780727425,
      "profit": null
    },
    {
      "time": 1780737860,
      "profit": null
    },
    {
      "time": 1780843839,
      "profit": null
    },
    {
      "time": 1780963448,
      "profit": null
    },
    {
      "time": 1781028120,
      "profit": null
    },
    {
      "time": 1781085362,
      "profit": null
    },
    {
      "time": 1781196822,
      "profit": null
    },
    {
      "time": 1781215315,
      "profit": null
    },
    {
      "time": 1781258934,
      "profit": null
    },
    {
      "time": 1781273375,
      "profit": null
    },
    {
      "time": 1781309927,
      "profit": null
    },
    {
      "time": 1781358938,
      "profit": null
    },
    {
      "time": 1781409163,
      "profit": null
    },
    {
      "time": 1781436540,
      "profit": null
    },
    {
      "time": 1781457543,
      "profit": null
    },
    {
      "time": 1781465026,
      "profit": null
    },
    {
      "time": 1781601921,
      "profit": null
    },
    {
      "time": 1781622502,
      "profit": null
    },
    {
      "time": 1781720009,
      "profit": null
    },
    {
      "time": 1781754172,
      "profit": null
    },
    {
      "time": 1781772313,
      "profit": null
    },
    {
      "time": 1781828694,
      "profit": null
    },
    {
      "time": 1781868034,
      "profit": null
    },
    {
      "time": 1781909697,
      "profit": null
    },
    {
      "time": 1781914074,
      "profit": null
    },
    {
      "time": 1781932284,
      "profit": null
    },
    {
      "time": 1781945564,
      "profit": null
    },
    {
      "time": 1782065898,
      "profit": null
    },
    {
      "time": 1782216285,
      "profit": null
    },
    {
      "time": 1782229549,
      "profit": null
    },
    {
      "time": 1782271448,
      "profit": null
    },
    {
      "time": 1782286682,
      "profit": null
    },
    {
      "time": 1782307227,
      "profit": null
    },
    {
      "time": 1782317965,
      "profit": null
    },
    {
      "time": 1782327025,
      "profit": null
    },
    {
      "time": 1782407455,
      "profit": null
    },
    {
      "time": 1782546471,
      "profit": null
    },
    {
      "time": 1782576193,
      "profit": null
    },
    {
      "time": 1782684532,
      "profit": null
    },
    {
      "time": 1782730440,
      "profit": null
    }
  ]
}
