{
  "chartType": "line",
  "meta": {
    "title": "Necklace mould",
    "description": "Daily profit trend"
  },
  "xKey": "time",
  "series": [
    {
      "dataKey": "profit",
      "label": "Profit",
      "valueFormat": "integer"
    }
  ],
  "data": [
    {
      "time": 1781638381,
      "profit": null
    },
    {
      "time": 1781647794,
      "profit": null
    },
    {
      "time": 1781655267,
      "profit": null
    },
    {
      "time": 1781772313,
      "profit": null
    },
    {
      "time": 1781828694,
      "profit": null
    },
    {
      "time": 1781881847,
      "profit": null
    },
    {
      "time": 1781891700,
      "profit": null
    }
  ]
}
